pyomodoro/__init__.py
pyomodoro/__main__.py
pyomodoro/cli.py
pyomodoro/locale/__init__.py
pyomodoro/locale/en_US.yml
pyomodoro/locale/es_ES.yml
pyomodoro/resources/__init__.py
pyomodoro/resources/pyomodoro.ico
pyomodoro/resources/pyomodoro.png
pyomodoro/tests/__init__.py
pyomodoro/tests/test_cli.py
pyomodoro/tests/resources/__init__.py
pyomodoro/tests/resources/good_config.yml
pyomodoro/tests/resources/good_es_config.yml
pyomodoro/tests/resources/hanging_quote_config.yml
pyomodoro/tests/resources/interval_values_config.yml
pyomodoro/tests/resources/nested_config.yml
pyomodoro/tests/resources/non_existant_es_language_config.yml
pyomodoro-1.0.0.dist-info/LICENSE
pyomodoro-1.0.0.dist-info/METADATA
pyomodoro-1.0.0.dist-info/WHEEL
pyomodoro-1.0.0.dist-info/entry_points.txt
pyomodoro-1.0.0.dist-info/top_level.txt
pyomodoro-1.0.0.dist-info/RECORD
