Metadata-Version: 2.1
Name: pyomodoro
Version: 1.0.0
Summary: An easy to use CLI for the Pomodoro Technique.
Home-page: https://gitlab.com/tedtramonte/pyomodoro
Author: Ted Tramonte
License: MIT
Project-URL: Issue tracker, https://gitlab.com/tedtramonte/pyomodoro/issues
Platform: UNKNOWN
Classifier: Development Status :: 5 - Production/Stable
Classifier: License :: OSI Approved :: MIT License
Classifier: Intended Audience :: End Users/Desktop
Classifier: Intended Audience :: Information Technology
Classifier: Intended Audience :: Education
Classifier: Natural Language :: English
Classifier: Operating System :: OS Independent
Classifier: Programming Language :: Python :: 3.7
Classifier: Programming Language :: Python :: 3.8
Classifier: Programming Language :: Python :: 3.9
Classifier: Topic :: Education
Classifier: Topic :: Office/Business :: Scheduling
Classifier: Topic :: Other/Nonlisted Topic
Classifier: Topic :: Scientific/Engineering
Classifier: Topic :: Utilities
Requires-Python: >=3.7
Requires-Dist: Click (==7.1.2)
Requires-Dist: plyer (==1.4.3)
Requires-Dist: PyYAML (==5.3.1)
Requires-Dist: python-i18n[yaml] (==0.3.9)
